{"sections":{"featured-text":{"type":"featured-text","settings":{"background-color":"light","light-text":false,"container-width":4,"spacing-above":true,"spacing-below":true,"overline":"","heading":"Welcome To Inside Stores","text":"<p>Your Premier Destination for Designer Fabrics and Wallpapers<\/p>"}},"grid-with-overlay":{"type":"grid-with-overlay","blocks":{"overlay-block-0":{"type":"image","settings":{"image":"shopify:\/\/shop_images\/phillip-jeffries-wallpaper.jpg","wide":true,"tall":true,"retain-ratio":false,"title":"Phillip Jeffries Wallpaper","link-url":"shopify:\/\/collections\/phillip-jeffries-wallpaper","link-text":"View more"}},"overlay-block-2":{"type":"image","settings":{"image":"shopify:\/\/shop_images\/textured-wallpaper-innovations.jpg","wide":false,"tall":false,"retain-ratio":false,"title":"Innovations Wallpaper","link-url":"shopify:\/\/collections\/innovations","link-text":"View more"}},"overlay-block-1":{"type":"image","settings":{"image":"shopify:\/\/shop_images\/peel-and-stick-wallcovering.jpg","wide":false,"tall":false,"retain-ratio":false,"title":"York Wallpaper","link-url":"shopify:\/\/collections\/york-wallcoverings","link-text":"View more"}},"overlay-block-3":{"type":"image","settings":{"image":"shopify:\/\/shop_images\/schumacher-wallpaper.jpg","wide":false,"tall":false,"retain-ratio":false,"title":"Schumacher Wallpaper","link-url":"shopify:\/\/collections\/f-schumacher-wallpaper","link-text":"View more"}},"c8581f2a-7f6a-4472-ac33-b941dbdd11fd":{"type":"image","settings":{"image":"shopify:\/\/shop_images\/scalamandrewallpaper_f149389a-8634-4c34-b7e2-55643ae8f32f.jpg","wide":false,"tall":false,"retain-ratio":false,"title":"Scalamandre Wallpaper","link-url":"shopify:\/\/collections\/scalamandre-wallpaper","link-text":"View more"}},"e80a1369-b1cf-4a74-b095-762c3393c2a7":{"type":"image","settings":{"image":"shopify:\/\/shop_images\/kravet-wallpaper.jpg","wide":false,"tall":false,"retain-ratio":false,"title":"Kravet Wallpaper","link-url":"shopify:\/\/collections\/kravet-wallpaper","link-text":"View more"}},"1f5f82c9-070b-4b7f-811e-8877f74fcc26":{"type":"image","settings":{"image":"shopify:\/\/shop_images\/clarkandclarkwallpaper.jpg","wide":false,"tall":false,"retain-ratio":false,"title":"Clark and Clark Wallpaper","link-url":"shopify:\/\/collections\/clarke-and-clarke-wallpaper","link-text":"View more"}},"f5b7c715-3fe9-4163-87c7-84b9f8b23d01":{"type":"image","settings":{"image":"shopify:\/\/shop_images\/groundworkswallpaper_9f67f282-db5f-4520-ba16-39cd27081f64.jpg","wide":false,"tall":false,"retain-ratio":false,"title":"Groundworks Wallpaper","link-url":"shopify:\/\/collections\/groundworks-wallpapers","link-text":"View more"}},"b78b363b-8ad5-48a5-becd-27346a884154":{"type":"image","settings":{"image":"shopify:\/\/shop_images\/coleandsonwallpaper.jpg","wide":false,"tall":false,"retain-ratio":false,"title":"Cole & Son Wallpaper","link-url":"shopify:\/\/collections\/cole-and-sons-wallpaper","link-text":"View more"}},"a745e05b-d172-441a-8dec-12556072861c":{"type":"image","disabled":true,"settings":{"wide":false,"tall":false,"retain-ratio":false,"title":"Grid image","link-url":"","link-text":"View more"}}},"block_order":["overlay-block-0","overlay-block-2","overlay-block-1","overlay-block-3","c8581f2a-7f6a-4472-ac33-b941dbdd11fd","e80a1369-b1cf-4a74-b095-762c3393c2a7","1f5f82c9-070b-4b7f-811e-8877f74fcc26","f5b7c715-3fe9-4163-87c7-84b9f8b23d01","b78b363b-8ad5-48a5-becd-27346a884154","a745e05b-d172-441a-8dec-12556072861c"],"settings":{"text-style":"box","background-color":"none","spacing":true,"mobile-overlay":true,"container-width":6,"spacing-above":true,"spacing-below":true,"width":3,"mobile-width":"2","heading":"Explore Wallpaper","subtitle":"","link-url":"","link-text":""}},"164016757166a86406":{"type":"image-with-text","settings":{"text-color":"auto","background-color":"none","container-width":6,"spacing-above":false,"spacing-below":false,"image-height":2,"darken-image":false,"parallax-enabled":false,"text-position":"center","text-width":"medium","overlap":false,"box-around-text":true,"mobile-overlay":true,"image":"shopify:\/\/shop_images\/PhillipJeffriesWallpaper_360f724a-498d-4dc6-b350-14e925e23f72.jpg","overline":"New Wallpaper","title":"Fresh and New","description":"<p>Thousands of new patterns just arrived this week.  <\/p>","link-url":"shopify:\/\/collections\/new-wallpaper-arrivals","link-text":""}},"1640167859b5c16893":{"type":"grid-with-overlay","blocks":{"1640167859a1c96a93-0":{"type":"image","settings":{"image":"shopify:\/\/shop_images\/schumacherfabric.jpg","wide":false,"tall":false,"retain-ratio":false,"title":"Schumacher Fabric","link-url":"shopify:\/\/collections\/f-schumacher-fabric","link-text":"View more"}},"1640167859a1c96a93-1":{"type":"image","settings":{"image":"shopify:\/\/shop_images\/kravetfabric.jpg","wide":false,"tall":false,"retain-ratio":false,"title":"Kravet Fabric","link-url":"shopify:\/\/collections\/kravet-fabrics","link-text":"View more"}},"1640167859a1c96a93-2":{"type":"image","settings":{"image":"shopify:\/\/shop_images\/scalamandre-fabric_b6b3369d-1577-493f-9389-74be967b798c.jpg","wide":false,"tall":false,"retain-ratio":false,"title":"Scalamandre Fabric","link-url":"shopify:\/\/collections\/scalamandre-fabric","link-text":"View more"}},"1640167859a1c96a93-3":{"type":"image","settings":{"image":"shopify:\/\/shop_images\/clarkeandclarkefabric_53ea519e-fe71-4930-8e2d-6fd708d3fa7f.jpg","wide":false,"tall":false,"retain-ratio":false,"title":"Clarke and Clarke Fabric","link-url":"shopify:\/\/collections\/clarke-and-clarke-fabric","link-text":"View more"}},"d6ae2379-05cb-42f9-9bee-e83df8324047":{"type":"image","settings":{"image":"shopify:\/\/shop_images\/groundworksfabric.jpg","wide":false,"tall":false,"retain-ratio":false,"title":"Groundworks Fabric","link-url":"shopify:\/\/collections\/groundworks-fabric","link-text":"View more"}},"ef42088c-fd17-4d4b-9aa0-ac42f62d5bbe":{"type":"image","settings":{"image":"shopify:\/\/shop_images\/leejofafabric_7f3e6f5f-142a-4f6a-adff-dc99b9ca2ca4.jpg","wide":false,"tall":false,"retain-ratio":false,"title":"Lee Jofa Fabric","link-url":"shopify:\/\/collections\/lee-jofa-fabric","link-text":"View more"}},"1a5a4e1a-9143-48ce-8e82-0f0953d2c770":{"type":"image","disabled":true,"settings":{"wide":false,"tall":false,"retain-ratio":false,"title":"Grid image","link-url":"","link-text":"View more"}},"c2ab6290-9cde-4230-85ac-e32b1a8256bb":{"type":"image","disabled":true,"settings":{"wide":false,"tall":false,"retain-ratio":false,"title":"Grid image","link-url":"","link-text":"View more"}}},"block_order":["1640167859a1c96a93-0","1640167859a1c96a93-1","1640167859a1c96a93-2","1640167859a1c96a93-3","d6ae2379-05cb-42f9-9bee-e83df8324047","ef42088c-fd17-4d4b-9aa0-ac42f62d5bbe","1a5a4e1a-9143-48ce-8e82-0f0953d2c770","c2ab6290-9cde-4230-85ac-e32b1a8256bb"],"settings":{"text-style":"box","background-color":"none","spacing":true,"mobile-overlay":true,"container-width":6,"spacing-above":true,"spacing-below":true,"width":3,"mobile-width":"2","heading":"Discover Fabric","subtitle":"","link-url":"","link-text":""}},"1650308039155cb4a2":{"type":"image-with-text","settings":{"text-color":"auto","background-color":"none","container-width":6,"spacing-above":false,"spacing-below":false,"image-height":2,"darken-image":false,"parallax-enabled":false,"text-position":"center","text-width":"medium","overlap":false,"box-around-text":true,"mobile-overlay":false,"image":"shopify:\/\/shop_images\/newfabricarrivals.jpg","overline":"Just Arrived","title":"New Fabrics This Week","description":"<p> <\/p>","link-url":"shopify:\/\/collections\/new-fabric-arrivals","link-text":""}},"featured-blog":{"type":"featured-blog","settings":{"background-color":"none","light-text":false,"container-width":4,"spacing-above":true,"spacing-below":true,"blog-heading":"The Design Life","blog":"news","tag-select":"pinned","show-date":true,"show-excerpt":false,"view-more-text":"View more"}},"16401814158380a11c":{"type":"image-with-text","settings":{"text-color":"auto","background-color":"none","container-width":6,"spacing-above":false,"spacing-below":true,"image-height":2,"darken-image":false,"parallax-enabled":false,"text-position":"center","text-width":"medium","overlap":false,"box-around-text":true,"mobile-overlay":false,"image":"shopify:\/\/shop_images\/slider-1204021.png","overline":"","title":"Luxury Brands","description":"<p>Need access to brands that are only available to the trade?  We can help.    See all the lines we carry, all at the same great pricing and delightful service.<\/p>","link-url":"shopify:\/\/pages\/luxury-brands","link-text":""}}},"order":["featured-text","grid-with-overlay","164016757166a86406","1640167859b5c16893","1650308039155cb4a2","featured-blog","16401814158380a11c"]}